main.py
jakana-0.1.0.dist-info/licenses/LICENSE
jakana-0.1.0.dist-info/METADATA
jakana-0.1.0.dist-info/WHEEL
jakana-0.1.0.dist-info/top_level.txt
jakana-0.1.0.dist-info/RECORD
