Metadata-Version: 2.4
Name: jakana
Version: 0.1.0
Summary: Learn Japanese kana
Requires-Python: >=3.13
License-File: LICENSE
Dynamic: license-file
